_zroya.cp36-win32.pyd
zroya/__init__.py
zroya/dismiss_reason.py
zroya/template_enums.py
zroya/version.py
zroya-0.2.4.dist-info/DESCRIPTION.rst
zroya-0.2.4.dist-info/METADATA
zroya-0.2.4.dist-info/RECORD
zroya-0.2.4.dist-info/WHEEL
zroya-0.2.4.dist-info/metadata.json
zroya-0.2.4.dist-info/top_level.txt
