Metadata-Version: 2.0
Name: zroya
Version: 0.2.4
Summary: Python library for creating native Windows notifications.
Home-page: https://malja.github.io/zroya
Author: Jan Malčák
Author-email: looorin@gmail.com
License: MIT
Keywords: notifications,windows,toast
Platform: UNKNOWN
Classifier: Development Status :: 4 - Beta
Classifier: Environment :: Win32 (MS Windows)
Classifier: License :: OSI Approved :: MIT License
Classifier: Operating System :: Microsoft :: Windows
Classifier: Programming Language :: C
Classifier: Programming Language :: C++
Classifier: Programming Language :: Python :: 3
Classifier: Topic :: Software Development :: User Interfaces
